ftd/__init__.py
ftd-0.1.6.dist-info/METADATA
ftd-0.1.6.dist-info/WHEEL
ftd-0.1.6.dist-info/top_level.txt
ftd-0.1.6.dist-info/RECORD
