Metadata-Version: 2.1
Name: ftd
Version: 0.1.6
Summary: Python Binding For FTD
Home-page: https://github.com/FifthTry/ftd-py
Author: Amit Upadhyay
Author-email: upadhyay@gmail.com
License: UNKNOWN
Project-URL: Bug Tracker, https://github.com/FifthTry/ftd-py/issues
Platform: UNKNOWN
Requires-Python: >=3.6
Requires-Dist: ftd-sys (>=0.1.4)
